eagle/__init__.py
eagle/logger.py
eagle/paw.py
eagle/eagle_datastore/data_refs/group_tickers.json
eagle/eagle_datastore/vnd_datastore/info/vn_by_symbol.json
eagle/eagle_downloader/__init__.py
eagle/eagle_downloader/vnd_downloader/__init__.py
eagle/eagle_downloader/vnd_downloader/qnaut.py
eagle/eagle_heart/__init__.py
eagle/eagle_heart/config.ini
eagle/eagle_heart/configs.py
eagle/eagle_heart/constant.py
eagle/eagle_heart/data_classes.py
eagle/eagle_heart/data_utils.py
tests/__init__.py
tests/calculate_alpha.py
tests/count_num_tickers.py
tests/inspect_data.py
tests/merge_tickers_group.py
tests/scan_data.py
tests/test_api.py
tests/test_data_in_mins.py
tests/test_stock_builder.py
tests/verify_data.py
eagle_kaist-0.0.1.dist-info/LICENSE
eagle_kaist-0.0.1.dist-info/METADATA
eagle_kaist-0.0.1.dist-info/WHEEL
eagle_kaist-0.0.1.dist-info/top_level.txt
eagle_kaist-0.0.1.dist-info/RECORD
